midi_markdown/__init__.py
midi_markdown/__main__.py
midi_markdown/constants.py
midi_markdown/alias/__init__.py
midi_markdown/alias/computation.py
midi_markdown/alias/conditionals.py
midi_markdown/alias/errors.py
midi_markdown/alias/imports.py
midi_markdown/alias/models.py
midi_markdown/alias/resolver.py
midi_markdown/cli/__init__.py
midi_markdown/cli/encoding_utils.py
midi_markdown/cli/error_handler.py
midi_markdown/cli/errors.py
midi_markdown/cli/main.py
midi_markdown/cli/progress.py
midi_markdown/cli/commands/__init__.py
midi_markdown/cli/commands/cheatsheet.py
midi_markdown/cli/commands/check.py
midi_markdown/cli/commands/compile.py
midi_markdown/cli/commands/examples.py
midi_markdown/cli/commands/inspect.py
midi_markdown/cli/commands/library.py
midi_markdown/cli/commands/play.py
midi_markdown/cli/commands/ports.py
midi_markdown/cli/commands/repl.py
midi_markdown/cli/commands/validate.py
midi_markdown/cli/commands/version.py
midi_markdown/codegen/__init__.py
midi_markdown/codegen/csv_export.py
midi_markdown/codegen/json_export.py
midi_markdown/codegen/midi_file.py
midi_markdown/core/__init__.py
midi_markdown/core/compiler.py
midi_markdown/core/ir.py
midi_markdown/diagnostics/__init__.py
midi_markdown/diagnostics/formatter.py
midi_markdown/expansion/__init__.py
midi_markdown/expansion/errors.py
midi_markdown/expansion/expander.py
midi_markdown/expansion/loops.py
midi_markdown/expansion/modulation.py
midi_markdown/expansion/random.py
midi_markdown/expansion/sweeps.py
midi_markdown/expansion/variables.py
midi_markdown/midi/__init__.py
midi_markdown/midi/events.py
midi_markdown/midi/generator.py
midi_markdown/parser/__init__.py
midi_markdown/parser/ast_nodes.py
midi_markdown/parser/mmd.lark
midi_markdown/parser/parser.py
midi_markdown/parser/transformer.py
midi_markdown/runtime/__init__.py
midi_markdown/runtime/completer.py
midi_markdown/runtime/midi_io.py
midi_markdown/runtime/player.py
midi_markdown/runtime/repl.py
midi_markdown/runtime/repl_state.py
midi_markdown-0.1.0.dist-info/METADATA
midi_markdown-0.1.0.dist-info/WHEEL
midi_markdown-0.1.0.dist-info/entry_points.txt
midi_markdown-0.1.0.dist-info/licenses/LICENSE
midi_markdown-0.1.0.dist-info/RECORD
