Metadata-Version: 2.4
Name: midi-markdown
Version: 0.1.0
Summary: Human-readable MIDI markup language compiler and tools
Project-URL: Homepage, https://github.com/cjgdev/midi-markdown
Project-URL: Repository, https://github.com/cjgdev/midi-markdown
Project-URL: Issues, https://github.com/cjgdev/midi-markdown/issues
Project-URL: Documentation, https://github.com/cjgdev/midi-markdown#readme
Author-email: Christopher Gilbert <your.email@example.com>
License: MIT
License-File: LICENSE
Keywords: automation,dsl,markup,midi,music
Classifier: Development Status :: 3 - Alpha
Classifier: Intended Audience :: Developers
Classifier: Intended Audience :: End Users/Desktop
Classifier: License :: OSI Approved :: MIT License
Classifier: Programming Language :: Python :: 3
Classifier: Programming Language :: Python :: 3.12
Classifier: Topic :: Multimedia :: Sound/Audio :: MIDI
Classifier: Typing :: Typed
Requires-Python: >=3.12
Requires-Dist: lark>=1.3.1
Requires-Dist: mido>=1.3.0
Requires-Dist: prompt-toolkit>=3.0.0
Requires-Dist: python-rtmidi>=1.5.0
Requires-Dist: pyyaml>=6.0
Requires-Dist: readchar>=4.2.1
Requires-Dist: rich>=13.0.0
Requires-Dist: typer>=0.12.0
Provides-Extra: dev
Requires-Dist: mypy>=1.11.0; extra == 'dev'
Requires-Dist: pexpect>=4.9.0; extra == 'dev'
Requires-Dist: pre-commit>=3.5.0; extra == 'dev'
Requires-Dist: pytest-cov>=4.0.0; extra == 'dev'
Requires-Dist: pytest-mock>=3.12.0; extra == 'dev'
Requires-Dist: pytest>=8.0.0; extra == 'dev'
Requires-Dist: ruff>=0.6.0; extra == 'dev'
Requires-Dist: types-pyyaml>=6.0.0; extra == 'dev'
Provides-Extra: docs
Requires-Dist: mkdocs-include-markdown-plugin>=6.0.0; extra == 'docs'
Requires-Dist: mkdocs-material>=9.5.0; extra == 'docs'
Requires-Dist: mkdocs>=1.6.0; extra == 'docs'
Requires-Dist: mkdocstrings-python>=1.8.0; extra == 'docs'
Requires-Dist: mkdocstrings>=0.24.0; extra == 'docs'
Requires-Dist: pymdown-extensions>=10.7.0; extra == 'docs'
